putdig_cli/__init__.py
putdig_cli/pumbench.py
putdig_cli/pumgen.py
putdig_cli/puminj.py
putdig_cli/pumqry.py
PuTDIG_CLI-0.0.6.dist-info/METADATA
PuTDIG_CLI-0.0.6.dist-info/WHEEL
PuTDIG_CLI-0.0.6.dist-info/entry_points.txt
PuTDIG_CLI-0.0.6.dist-info/top_level.txt
PuTDIG_CLI-0.0.6.dist-info/RECORD
