Metadata-Version: 2.1
Name: PuTDIG-CLI
Version: 0.0.6
Summary: Common interface and business logic for PuTDIG and PuTDIG-CLI
Home-page: https://github.com/PumpkinSpace/PuTDIG-CLI
Author: James Womack, Jack Hughes
Author-email: info@pumpkininc.com
License: UNKNOWN
Platform: UNKNOWN
Classifier: Programming Language :: Python :: 3
Classifier: License :: OSI Approved :: MIT License
Classifier: Operating System :: OS Independent
Requires-Python: >=3.7
Requires-Dist: pumpkin-supmcu
Requires-Dist: putdig-common
